{
  "meta": {
    "created_date": "2024-09-13T19:51:41",
    "updated_date": "2024-09-13T19:52:03",
    "field_reference": "https://developer.wordpress.org/rest-api/reference/pages/",
    "api_version": "v2",
    "api_url": "https://live-testmj-com.pantheonsite.io/wp-json/wp/v2/",
    "object_url": "https://live-testmj-com.pantheonsite.io/wp-json/wp/v2/pages/20044",
    "process": {
      "source_code": "https://github.com/cagov/wordpress-to-github",
      "source_data": "https://live-testmj-com.pantheonsite.io",
      "deployment_target": "https://github.com/mukkhtarr/static-content-testmj/tree/main"
    },
    "refresh_frequency": "as needed"
  },
  "data": {
    "id": 20044,
    "date": "2024-09-13T12:51:41",
    "date_gmt": "2024-09-13T19:51:41",
    "guid": "https://live-testmj-com.pantheonsite.io/?page_id=20044",
    "modified": "2024-09-13T12:52:03",
    "modified_gmt": "2024-09-13T19:52:03",
    "slug": "conversions-for-cultivation-licensees",
    "status": "publish",
    "type": "page",
    "link": "https://live-testmj-com.pantheonsite.io/conversions-for-cultivation-licensees/",
    "title": "Conversions for cultivation licensees",
    "excerpt": "<p>Starting January 1, 2023, an eligible licensee may convert active and previously active cultivation licenses into a Large (Type 5, 5A, or 5B) or Medium cultivation license. Additionally, a licensee may hold more than one Medium cultivation license.</p>\n",
    "author": 32,
    "featured_media": 0,
    "parent": 0,
    "menu_order": 0,
    "comment_status": "closed",
    "ping_status": "closed",
    "template": "",
    "meta": {
      "_stopmodifiedupdate": false,
      "_modified_date": ""
    },
    "categories": [
      "Resources"
    ],
    "tags": [],
    "design_system_fields": {
      "template": "page"
    },
    "og_meta": {
      "editor": {
        "platform": "WordPress",
        "plugin": "autodescription",
        "plugin_name": "The SEO Framework",
        "plugin_version": "4.1.5.1",
        "editor_url": "https://live-testmj-com.pantheonsite.io"
      },
      "site_name": "Department of Cannabis Control",
      "site_description": "Learn about California cannabis laws and licenses",
      "site_url": "https://live-testmj-com.pantheonsite.io",
      "canonical_url": "https://live-testmj-com.pantheonsite.io/conversions-for-cultivation-licensees/",
      "page_title": "Conversions for cultivation licensees",
      "page_description": "Learn about California cannabis laws and licenses",
      "page_social_image_url": "https://api.cannabis.ca.gov/wp-content/uploads/2021/07/cropped-Cannabis_horizontal_social.png",
      "page_social_image_width": 1200,
      "page_social_image_height": 630,
      "page_social_image_alt": "",
      "meta_title": "Conversions for cultivation licensees",
      "meta_description": "Learn about California cannabis laws and licenses",
      "meta_canonical_url": "https://live-testmj-com.pantheonsite.io/conversions-for-cultivation-licensees/",
      "open_graph_title": "Conversions for cultivation licensees",
      "open_graph_description": "Learn about California cannabis laws and licenses",
      "twitter_title": "Conversions for cultivation licensees",
      "twitter_description": "Learn about California cannabis laws and licenses"
    },
    "headless_categories": [
      {
        "term_id": 809,
        "name": "Resources",
        "slug": "resources",
        "term_group": 0,
        "term_taxonomy_id": 809,
        "taxonomy": "category",
        "description": "",
        "parent": 0,
        "filter": "raw",
        "cat_ID": 809,
        "category_description": "",
        "cat_name": "Resources",
        "category_nicename": "resources",
        "category_parent": 0
      }
    ],
    "headless_tags": [],
    "headless_publishing": [],
    "headless_preview": [],
    "wordpress_url": "https://live-testmj-com.pantheonsite.io/conversions-for-cultivation-licensees/"
  }
}