{
  "meta": {
    "created_date": "2025-07-22T20:24:58",
    "updated_date": "2025-07-22T20:24:59",
    "field_reference": "https://developer.wordpress.org/rest-api/reference/posts/",
    "api_version": "v2",
    "api_url": "https://live-testmj-com.pantheonsite.io/wp-json/wp/v2/",
    "object_url": "https://live-testmj-com.pantheonsite.io/wp-json/wp/v2/posts/21555",
    "process": {
      "source_code": "https://github.com/cagov/wordpress-to-github",
      "source_data": "https://live-testmj-com.pantheonsite.io",
      "deployment_target": "https://github.com/mukkhtarr/static-content-testmj/tree/main"
    },
    "refresh_frequency": "as needed"
  },
  "data": {
    "id": 21555,
    "date": "2025-07-22T13:24:58",
    "date_gmt": "2025-07-22T20:24:58",
    "guid": "https://live-testmj-com.pantheonsite.io/?p=21555",
    "modified": "2025-07-22T13:24:59",
    "modified_gmt": "2025-07-22T20:24:59",
    "slug": "form-dcc-1203-language-access-complaint",
    "status": "publish",
    "type": "post",
    "link": "https://live-testmj-com.pantheonsite.io/2025/07/form-dcc-1203-language-access-complaint/",
    "title": "Form DCC-1203: Language Access Complaint",
    "excerpt": "<p>Language Access, Interpreter, or Translation Complaint</p>\n",
    "author": 52,
    "featured_media": 0,
    "comment_status": "closed",
    "ping_status": "closed",
    "sticky": false,
    "template": "",
    "format": "standard",
    "meta": {
      "_stopmodifiedupdate": false,
      "_modified_date": ""
    },
    "categories": [
      "All"
    ],
    "tags": [],
    "design_system_fields": {
      "template": "post"
    },
    "og_meta": {
      "editor": {
        "platform": "WordPress",
        "plugin": "autodescription",
        "plugin_name": "The SEO Framework",
        "plugin_version": "4.1.5.1",
        "editor_url": "https://live-testmj-com.pantheonsite.io"
      },
      "site_name": "Department of Cannabis Control",
      "site_description": "Learn about California cannabis laws and licenses",
      "site_url": "https://live-testmj-com.pantheonsite.io",
      "canonical_url": "https://live-testmj-com.pantheonsite.io/2025/07/form-dcc-1203-language-access-complaint/",
      "page_title": "Form DCC-1203: Language Access Complaint",
      "page_description": "Learn about California cannabis laws and licenses",
      "page_social_image_url": "https://api.cannabis.ca.gov/wp-content/uploads/2021/07/cropped-Cannabis_horizontal_social.png",
      "page_social_image_width": 1200,
      "page_social_image_height": 630,
      "page_social_image_alt": "",
      "meta_title": "Form DCC-1203: Language Access Complaint",
      "meta_description": "Learn about California cannabis laws and licenses",
      "meta_canonical_url": "https://live-testmj-com.pantheonsite.io/2025/07/form-dcc-1203-language-access-complaint/",
      "open_graph_title": "Form DCC-1203: Language Access Complaint",
      "open_graph_description": "Learn about California cannabis laws and licenses",
      "twitter_title": "Form DCC-1203: Language Access Complaint",
      "twitter_description": "Learn about California cannabis laws and licenses"
    },
    "headless_categories": [
      {
        "term_id": 1,
        "name": "All",
        "slug": "all",
        "term_group": 0,
        "term_taxonomy_id": 1,
        "taxonomy": "category",
        "description": "",
        "parent": 0,
        "filter": "raw",
        "cat_ID": 1,
        "category_description": "",
        "cat_name": "All",
        "category_nicename": "all",
        "category_parent": 0
      }
    ],
    "headless_tags": [],
    "headless_publishing": [],
    "headless_preview": [],
    "event": null,
    "custom_post_date": "",
    "meta_": {
      "0": "",
      "custom_post_link": "",
      "custom_post_date": "",
      "custom_post_location": ""
    },
    "wordpress_url": "https://live-testmj-com.pantheonsite.io/2025/07/form-dcc-1203-language-access-complaint/"
  }
}